{"id": "15447551", "Veg": true, "url": "https://migusto.migros.ch/de/rezepte/gesalzene-erdnuss-fudges", "ingredients": [{"id": "17229", "is_main_ingredient": true, "text": "weisse Schokolade", "amount": {"is_approximate": false, "quantity": 100, "quantity_up_to": null, "text": "100 g", "unit": "g"}, "availability": null, "cultivar": null}, {"id": "16850", "is_main_ingredient": false, "text": "Butter", "amount": {"is_approximate": false, "quantity": 60, "quantity_up_to": null, "text": "60 g", "unit": "g"}, "availability": null, "cultivar": null}, {"id": "37000", "is_main_ingredient": false, "text": "gezuckerte Kondensmilch", "amount": {"is_approximate": false, "quantity": 250, "quantity_up_to": null, "text": "250 g", "unit": "g"}, "availability": null, "cultivar": null}, {"id": "60214", "is_main_ingredient": false, "text": "flüssiger Blütenhonig", "amount": {"is_approximate": false, "quantity": 80, "quantity_up_to": null, "text": "80 g", "unit": "g"}, "availability": null, "cultivar": null}, {"id": "17274", "is_main_ingredient": false, "text": "Rohrzucker", "amount": {"is_approximate": false, "quantity": 100, "quantity_up_to": null, "text": "100 g", "unit": "g"}, "availability": null, "cultivar": null}, {"id": "17064", "is_main_ingredient": true, "text": "gesalzene geröstete Erdnüsse", "amount": {"is_approximate": false, "quantity": 70, "quantity_up_to": null, "text": "70 g", "unit": "g"}, "availability": null, "cultivar": null}, {"id": "17206", "is_main_ingredient": false, "text": "Milchschokolade", "amount": {"is_approximate": false, "quantity": 150, "quantity_up_to": null, "text": "150 g", "unit": "g"}, "availability": null, "cultivar": null}, {"id": "16462", "is_main_ingredient": false, "text": "Salzflocken oder Fleur de sel zum Darüberstreuen", "amount": {"is_approximate": false, "quantity": 0, "quantity_up_to": null, "text": "", "unit": ""}, "availability": null, "cultivar": null}], "Vegan": true}